{
	"update_time":"2021.04.26 00:00",
	"date":"2021.04.23",
	"closed_positions": [
		{"order_id":75707361,"symbol":"USDCHF.p","type":"sell","vol":0.01,"opentime":"2021.04.19 16:32:08","closetime":"2021.04.23 21:13:49","commission":-0.07,"swap":-0.25,"profit":0.56},
		{"order_id":75709179,"symbol":"USDCHF.p","type":"sell","vol":0.01,"opentime":"2021.04.19 17:17:22","closetime":"2021.04.23 21:13:48","commission":-0.07,"swap":-0.25,"profit":2.08},
		{"order_id":75757085,"symbol":"USDJPY.p","type":"sell","vol":0.01,"opentime":"2021.04.21 10:36:52","closetime":"2021.04.22 03:48:39","commission":-0.07,"swap":-0.08,"profit":0.98},
		{"order_id":75758099,"symbol":"USDCHF.p","type":"sell","vol":0.01,"opentime":"2021.04.21 10:59:15","closetime":"2021.04.23 21:13:48","commission":-0.07,"swap":-0.17,"profit":3.95},
		{"order_id":75758214,"symbol":"USDJPY.p","type":"sell","vol":0.01,"opentime":"2021.04.21 11:02:01","closetime":"2021.04.22 03:48:39","commission":-0.07,"swap":-0.08,"profit":2.44},
		{"order_id":75790662,"symbol":"USDCHF.p","type":"sell","vol":0.01,"opentime":"2021.04.22 14:59:07","closetime":"2021.04.23 12:02:46","commission":-0.07,"swap":-0.04,"profit":0.56},
		{"order_id":75795873,"symbol":"EURUSD.p","type":"buy","vol":0.01,"opentime":"2021.04.22 16:20:52","closetime":"2021.04.23 10:15:55","commission":-0.07,"swap":-0.04,"profit":1.04},
		{"order_id":75795874,"symbol":"EURUSD.p","type":"buy","vol":0.01,"opentime":"2021.04.22 16:20:53","closetime":"2021.04.23 10:30:05","commission":-0.07,"swap":-0.04,"profit":1.16},
		{"order_id":75796389,"symbol":"USDCHF.p","type":"sell","vol":0.01,"opentime":"2021.04.22 16:25:34","closetime":"2021.04.23 12:02:46","commission":-0.07,"swap":-0.04,"profit":1.93},
		{"order_id":75800324,"symbol":"EURUSD.p","type":"buy","vol":0.01,"opentime":"2021.04.22 17:27:47","closetime":"2021.04.23 10:30:05","commission":-0.07,"swap":-0.04,"profit":3.83},
		{"order_id":75800353,"symbol":"USDCHF.p","type":"sell","vol":0.01,"opentime":"2021.04.22 17:28:35","closetime":"2021.04.23 12:02:45","commission":-0.07,"swap":-0.04,"profit":3.30},
		{"order_id":75800422,"symbol":"EURUSD.p","type":"buy","vol":0.01,"opentime":"2021.04.22 17:29:50","closetime":"2021.04.23 10:15:55","commission":-0.07,"swap":-0.04,"profit":4.03},
		{"order_id":75830346,"symbol":"USDCHF.p","type":"sell","vol":0.01,"opentime":"2021.04.23 17:18:23","closetime":"2021.04.23 20:05:54","commission":-0.07,"swap":0.00,"profit":2.17},
		{"order_id":75832827,"symbol":"EURUSD.p","type":"buy","vol":0.01,"opentime":"2021.04.23 18:04:18","closetime":"2021.04.23 19:28:41","commission":-0.07,"swap":0.00,"profit":1.79}],
	"closed_return":27.73,
	"closed_profit":0.31,
	"open_positions": [
		{"order_id":75772712,"symbol":"USDCAD.p","type":"sell","vol":0.01,"opentime":"2021.04.21 18:41:29","closetime":"0","commission":-0.07,"swap":-0.07,"profit":0.61},
		{"order_id":75772713,"symbol":"USDCAD.p","type":"sell","vol":0.01,"opentime":"2021.04.21 18:41:29","closetime":"0","commission":-0.07,"swap":-0.07,"profit":0.61},
		{"order_id":75775029,"symbol":"USDCAD.p","type":"sell","vol":0.01,"opentime":"2021.04.22 02:16:38","closetime":"0","commission":-0.07,"swap":-0.02,"profit":2.12},
		{"order_id":75775031,"symbol":"USDCAD.p","type":"sell","vol":0.01,"opentime":"2021.04.22 02:16:38","closetime":"0","commission":-0.07,"swap":-0.02,"profit":2.09},
		{"order_id":75780384,"symbol":"NZDUSD.p","type":"buy","vol":0.01,"opentime":"2021.04.22 08:21:53","closetime":"0","commission":-0.07,"swap":-0.01,"profit":0.30},
		{"order_id":75785351,"symbol":"USDJPY.p","type":"sell","vol":0.01,"opentime":"2021.04.22 11:53:00","closetime":"0","commission":-0.07,"swap":-0.03,"profit":1.98},
		{"order_id":75785413,"symbol":"NZDUSD.p","type":"buy","vol":0.01,"opentime":"2021.04.22 11:57:42","closetime":"0","commission":-0.07,"swap":-0.01,"profit":1.95},
		{"order_id":75796969,"symbol":"NZDUSD.p","type":"buy","vol":0.01,"opentime":"2021.04.22 16:33:49","closetime":"0","commission":-0.07,"swap":-0.01,"profit":1.31},
		{"order_id":75799227,"symbol":"USDCAD.p","type":"sell","vol":0.01,"opentime":"2021.04.22 17:11:09","closetime":"0","commission":-0.07,"swap":-0.02,"profit":3.75},
		{"order_id":75799228,"symbol":"USDCAD.p","type":"sell","vol":0.01,"opentime":"2021.04.22 17:11:10","closetime":"0","commission":-0.07,"swap":-0.02,"profit":3.74},
		{"order_id":75805420,"symbol":"NZDUSD.p","type":"buy","vol":0.01,"opentime":"2021.04.22 20:26:46","closetime":"0","commission":-0.07,"swap":-0.01,"profit":3.62},
		{"order_id":75825708,"symbol":"USDCAD.p","type":"sell","vol":0.01,"opentime":"2021.04.23 15:58:45","closetime":"0","commission":-0.07,"swap":0.00,"profit":2.08},
		{"order_id":75825709,"symbol":"USDCAD.p","type":"sell","vol":0.01,"opentime":"2021.04.23 15:58:45","closetime":"0","commission":-0.07,"swap":0.00,"profit":2.08},
		{"order_id":74990211,"symbol":"AUDJPY.p","type":"sell","vol":0.01,"opentime":"2021.03.23 08:18:54","closetime":"0","commission":-0.07,"swap":-0.39,"profit":0.35},
		{"order_id":74990213,"symbol":"AUDJPY.p","type":"sell","vol":0.01,"opentime":"2021.03.23 08:18:00","closetime":"0","commission":-0.07,"swap":-0.39,"profit":0.41},
		{"order_id":75009497,"symbol":"AUDJPY.p","type":"sell","vol":0.01,"opentime":"2021.03.25 03:36:47","closetime":"0","commission":-0.07,"swap":-0.34,"profit":-9.07},
		{"order_id":75009498,"symbol":"AUDJPY.p","type":"sell","vol":0.01,"opentime":"2021.03.25 03:36:47","closetime":"0","commission":-0.07,"swap":-0.34,"profit":-9.08},
		{"order_id":75011826,"symbol":"AUDJPY.p","type":"sell","vol":0.01,"opentime":"2021.03.25 05:27:28","closetime":"0","commission":-0.07,"swap":-0.34,"profit":-6.80},
		{"order_id":75011827,"symbol":"AUDJPY.p","type":"sell","vol":0.01,"opentime":"2021.03.25 05:27:29","closetime":"0","commission":-0.07,"swap":-0.34,"profit":-6.80},
		{"order_id":75113534,"symbol":"AUDJPY.p","type":"sell","vol":0.01,"opentime":"2021.03.26 14:25:20","closetime":"0","commission":-0.07,"swap":-0.33,"profit":-1.22},
		{"order_id":75113535,"symbol":"AUDJPY.p","type":"sell","vol":0.01,"opentime":"2021.03.26 14:25:21","closetime":"0","commission":-0.07,"swap":-0.33,"profit":-1.21},
		{"order_id":75737571,"symbol":"AUDNZD.p","type":"sell","vol":0.11,"opentime":"2021.04.20 17:46:27","closetime":"0","commission":-0.77,"swap":-0.31,"profit":-4.04},
		{"order_id":75738233,"symbol":"AUDNZD.p","type":"sell","vol":0.01,"opentime":"2021.04.07 03:09:21","closetime":"0","commission":-0.07,"swap":-0.07,"profit":5.42},
		{"order_id":75773745,"symbol":"AUDNZD.p","type":"sell","vol":0.01,"opentime":"2021.04.21 20:17:40","closetime":"0","commission":-0.07,"swap":-0.01,"profit":-1.26},
		{"order_id":75779092,"symbol":"AUDNZD.p","type":"sell","vol":0.01,"opentime":"2021.04.22 07:17:59","closetime":"0","commission":-0.07,"swap":0.00,"profit":-0.08},
		{"order_id":75785343,"symbol":"AUDNZD.p","type":"sell","vol":0.01,"opentime":"2021.04.22 11:52:45","closetime":"0","commission":-0.07,"swap":0.00,"profit":1.09},
		{"order_id":75721670,"symbol":"AUDUSD.p","type":"buy","vol":0.01,"opentime":"2021.04.14 17:32:06","closetime":"0","commission":-0.07,"swap":-0.24,"profit":3.98},
		{"order_id":75727853,"symbol":"AUDUSD.p","type":"buy","vol":0.01,"opentime":"2021.04.20 12:50:59","closetime":"0","commission":-0.07,"swap":-0.12,"profit":-2.98},
		{"order_id":75742111,"symbol":"AUDUSD.p","type":"buy","vol":0.01,"opentime":"2021.04.20 21:51:55","closetime":"0","commission":-0.07,"swap":-0.12,"profit":3.26},
		{"order_id":75339614,"symbol":"CADJPY.p","type":"buy","vol":0.02,"opentime":"2021.04.02 17:10:21","closetime":"0","commission":-0.14,"swap":-0.27,"profit":-30.20},
		{"order_id":75339615,"symbol":"CADJPY.p","type":"buy","vol":0.02,"opentime":"2021.04.02 17:10:21","closetime":"0","commission":-0.14,"swap":-0.27,"profit":-30.20},
		{"order_id":75385246,"symbol":"CADJPY.p","type":"buy","vol":0.01,"opentime":"2021.04.06 16:24:02","closetime":"0","commission":-0.07,"swap":-0.16,"profit":-9.17},
		{"order_id":75385247,"symbol":"CADJPY.p","type":"buy","vol":0.01,"opentime":"2021.04.06 16:24:03","closetime":"0","commission":-0.07,"swap":-0.16,"profit":-9.17},
		{"order_id":75637521,"symbol":"CADJPY.p","type":"buy","vol":0.01,"opentime":"2021.04.15 17:51:50","closetime":"0","commission":-0.07,"swap":-0.08,"profit":-2.40},
		{"order_id":75637524,"symbol":"CADJPY.p","type":"buy","vol":0.01,"opentime":"2021.04.15 17:51:50","closetime":"0","commission":-0.07,"swap":-0.08,"profit":-2.42},
		{"order_id":75453393,"symbol":"EURGBP.p","type":"buy","vol":0.06,"opentime":"2021.04.08 19:54:07","closetime":"0","commission":-0.42,"swap":-4.48,"profit":28.32},
		{"order_id":75470513,"symbol":"EURJPY.p","type":"buy","vol":0.01,"opentime":"2021.04.09 14:59:52","closetime":"0","commission":-0.07,"swap":-0.47,"profit":-0.11},
		{"order_id":75730058,"symbol":"EURJPY.p","type":"buy","vol":0.01,"opentime":"2021.04.20 14:20:34","closetime":"0","commission":-0.07,"swap":-0.19,"profit":-1.23},
		{"order_id":75735923,"symbol":"EURJPY.p","type":"buy","vol":0.01,"opentime":"2021.04.20 17:11:03","closetime":"0","commission":-0.07,"swap":-0.19,"profit":1.16},
		{"order_id":75761719,"symbol":"EURJPY.p","type":"buy","vol":0.01,"opentime":"2021.04.21 13:39:25","closetime":"0","commission":-0.07,"swap":-0.16,"profit":6.75},
		{"order_id":75700856,"symbol":"EURUSD.p","type":"buy","vol":0.01,"opentime":"2021.04.07 17:27:48","closetime":"0","commission":-0.07,"swap":-0.76,"profit":18.17},
		{"order_id":75719244,"symbol":"EURUSD.p","type":"buy","vol":0.01,"opentime":"2021.04.08 19:12:57","closetime":"0","commission":-0.07,"swap":-0.64,"profit":17.60},
		{"order_id":75739704,"symbol":"GBPJPY.p","type":"sell","vol":0.11,"opentime":"2021.04.20 18:34:08","closetime":"0","commission":-0.77,"swap":-2.39,"profit":69.75},
		{"order_id":75700360,"symbol":"GBPUSD.p","type":"buy","vol":0.06,"opentime":"2021.04.19 13:57:04","closetime":"0","commission":-0.42,"swap":-1.26,"profit":-17.76},
		{"order_id":75618266,"symbol":"NZDCAD.p","type":"buy","vol":0.01,"opentime":"2021.04.07 17:28:01","closetime":"0","commission":-0.07,"swap":-0.15,"profit":7.93},
		{"order_id":75637357,"symbol":"NZDCAD.p","type":"buy","vol":0.06,"opentime":"2021.04.15 17:49:40","closetime":"0","commission":-0.42,"swap":-0.36,"profit":-6.59},
		{"order_id":75768028,"symbol":"NZDCAD.p","type":"buy","vol":0.01,"opentime":"2021.04.21 17:00:07","closetime":"0","commission":-0.07,"swap":-0.04,"profit":-6.23},
		{"order_id":75768146,"symbol":"NZDCAD.p","type":"buy","vol":0.01,"opentime":"2021.04.21 17:01:05","closetime":"0","commission":-0.07,"swap":-0.04,"profit":-4.54},
		{"order_id":75770809,"symbol":"NZDCAD.p","type":"buy","vol":0.01,"opentime":"2021.04.21 17:46:36","closetime":"0","commission":-0.07,"swap":-0.04,"profit":-1.86},
		{"order_id":75806412,"symbol":"NZDCAD.p","type":"buy","vol":0.01,"opentime":"2021.04.22 21:15:08","closetime":"0","commission":-0.07,"swap":-0.02,"profit":2.95},
		{"order_id":74289371,"symbol":"NZDCHF.p","type":"buy","vol":0.01,"opentime":"2021.02.24 22:31:03","closetime":"0","commission":-0.07,"swap":0.27,"profit":-16.60},
		{"order_id":74289372,"symbol":"NZDCHF.p","type":"buy","vol":0.01,"opentime":"2021.02.24 22:31:03","closetime":"0","commission":-0.07,"swap":0.27,"profit":-16.58},
		{"order_id":75774873,"symbol":"NZDCHF.p","type":"buy","vol":0.01,"opentime":"2021.04.22 01:41:29","closetime":"0","commission":-0.07,"swap":0.02,"profit":-3.33},
		{"order_id":75774961,"symbol":"NZDCHF.p","type":"buy","vol":0.01,"opentime":"2021.04.22 02:01:22","closetime":"0","commission":-0.07,"swap":0.02,"profit":-3.31},
		{"order_id":75780241,"symbol":"NZDCHF.p","type":"buy","vol":0.01,"opentime":"2021.04.22 08:15:37","closetime":"0","commission":-0.07,"swap":0.02,"profit":-1.87},
		{"order_id":75780242,"symbol":"NZDCHF.p","type":"buy","vol":0.01,"opentime":"2021.04.22 08:15:37","closetime":"0","commission":-0.07,"swap":0.02,"profit":-1.87},
		{"order_id":75785354,"symbol":"NZDCHF.p","type":"buy","vol":0.01,"opentime":"2021.04.22 11:53:17","closetime":"0","commission":-0.07,"swap":0.02,"profit":-0.02},
		{"order_id":75785355,"symbol":"NZDCHF.p","type":"buy","vol":0.01,"opentime":"2021.04.22 11:53:17","closetime":"0","commission":-0.07,"swap":0.02,"profit":-0.02},
		{"order_id":74852338,"symbol":"NZDUSD.p","type":"buy","vol":0.01,"opentime":"2021.03.15 04:02:20","closetime":"0","commission":-0.07,"swap":-0.49,"profit":-0.29},
		{"order_id":74852419,"symbol":"NZDUSD.p","type":"buy","vol":0.01,"opentime":"2021.03.15 04:00:56","closetime":"0","commission":-0.07,"swap":-0.49,"profit":-0.11},
		{"order_id":75774960,"symbol":"NZDUSD.p","type":"buy","vol":0.01,"opentime":"2021.04.22 02:01:21","closetime":"0","commission":-0.07,"swap":-0.02,"profit":-0.71},
		{"order_id":75780530,"symbol":"NZDUSD.p","type":"buy","vol":0.01,"opentime":"2021.04.22 08:30:03","closetime":"0","commission":-0.07,"swap":-0.02,"profit":0.51},
		{"order_id":75785405,"symbol":"NZDUSD.p","type":"buy","vol":0.01,"opentime":"2021.04.22 11:56:19","closetime":"0","commission":-0.07,"swap":-0.02,"profit":1.82},
		{"order_id":74766975,"symbol":"USDCAD.p","type":"sell","vol":0.01,"opentime":"2021.03.11 22:29:36","closetime":"0","commission":-0.07,"swap":-0.82,"profit":3.44},
		{"order_id":74766976,"symbol":"USDCAD.p","type":"sell","vol":0.01,"opentime":"2021.03.11 11:10:06","closetime":"0","commission":-0.07,"swap":-0.82,"profit":8.40},
		{"order_id":75481153,"symbol":"USDCHF.p","type":"sell","vol":0.01,"opentime":"2021.04.09 20:51:13","closetime":"0","commission":-0.07,"swap":-0.62,"profit":10.72},
		{"order_id":75698910,"symbol":"USDCHF.p","type":"sell","vol":0.01,"opentime":"2021.04.07 16:26:56","closetime":"0","commission":-0.07,"swap":-0.80,"profit":14.62},
		{"order_id":75695438,"symbol":"USDJPY.p","type":"sell","vol":0.01,"opentime":"2021.04.08 14:34:23","closetime":"0","commission":-0.07,"swap":-0.44,"profit":12.67},
		{"order_id":75827770,"symbol":"USDJPY.p","type":"sell","vol":0.01,"opentime":"2021.04.23 16:41:05","closetime":"0","commission":-0.07,"swap":-0.03,"profit":-2.03},
		{"order_id":75830348,"symbol":"USDJPY.p","type":"sell","vol":0.01,"opentime":"2021.04.23 17:18:23","closetime":"0","commission":-0.07,"swap":-0.03,"profit":0.47}],
	"open_return":7.27,
	"open_profit":0.08,
	"account":{
		"balance":8843.24,
		"margin":221.78,
		"equity":10819.27
	}
}

